{"cameraMode":{"drawMode":0,"name":"Shaded","section":"Shading Mode"},"sceneLighting":true,"audioPlay":false,"sceneViewState":{"m_AlwaysRefresh":false,"showFog":true,"showSkybox":true,"showFlares":true,"showImageEffects":true,"showParticleSystems":true,"showVisualEffectGraphs":true,"m_FxEnabled":true},"in2DMode":false,"pivot":{"x":122.89859008789063,"y":88.32003784179688,"z":-10.597262382507325},"rotation":{"x":0.19288037717342378,"y":0.56064772605896,"z":-0.13624884188175202,"w":0.7936833500862122},"size":52.735477447509769,"orthographic":true}